pull_request_codecommit/__init__.py
pull_request_codecommit/aws/__init__.py
pull_request_codecommit/aws/client.py
pull_request_codecommit/config.py
pull_request_codecommit/git/__init__.py
pull_request_codecommit/git/client.py
pull_request_codecommit/git/commit.py
pull_request_codecommit/git/commits.py
pull_request_codecommit/git/message.py
pull_request_codecommit/git/remote.py
pull_request_codecommit/pull_request.py
pull_request_codecommit/pull_request_codecommit.py
pull_request_codecommit/pull_request_proposal.py
pull_request_codecommit/repository.py
pull_request_codecommit-1.0.0.dist-info/LICENSE.txt
pull_request_codecommit-1.0.0.dist-info/METADATA
pull_request_codecommit-1.0.0.dist-info/WHEEL
pull_request_codecommit-1.0.0.dist-info/entry_points.txt
pull_request_codecommit-1.0.0.dist-info/RECORD
