Metadata-Version: 2.3
Name: pull-request-codecommit
Version: 1.0.0
Summary: pull-request-codecommit creates a PR within CodeCommit based on your commit messages.
License: Apache2
Author: Joris Conijn
Author-email: joris@conijnonline.nl
Requires-Python: >=3.8,<4.0
Classifier: License :: Other/Proprietary License
Classifier: Programming Language :: Python :: 3
Classifier: Programming Language :: Python :: 3.8
Classifier: Programming Language :: Python :: 3.9
Classifier: Programming Language :: Python :: 3.10
Classifier: Programming Language :: Python :: 3.11
Classifier: Programming Language :: Python :: 3.12
Classifier: Programming Language :: Python :: 3.13
Requires-Dist: click (>=8.0.3,<9.0.0)
Requires-Dist: python-semantic-release (==10.0.2)
